speaches_cli/__init__.py
speaches_cli/main.py
speaches_cli-0.1.0.dist-info/METADATA
speaches_cli-0.1.0.dist-info/WHEEL
speaches_cli-0.1.0.dist-info/entry_points.txt
speaches_cli-0.1.0.dist-info/RECORD
