Metadata-Version: 2.4
Name: speaches-cli
Version: 0.1.0
Summary: Add your description here
Author-email: Fedir Zadniprovskyi <github.g1k56@simplelogin.com>
Requires-Python: ==3.12.*
Requires-Dist: httpx>=0.27.2
Requires-Dist: typer>=0.12.5
